{"schema_version":2,"terms":{"bathroom":["contribution-677b43fc5badd5d7","contribution-8507fba8b5afa879"],"breaks":["contribution-d8ebc95241ffbb4a","contribution-c4338830810367fa","contribution-8507fba8b5afa879"],"contrast":["contribution-695eeac45a3100ed"],"correction":["contribution-14bb08ef8d65c98a","contribution-ef4c2c008f7f46d8","contribution-bf5c1d914b1eff79","contribution-cc2141715d88129d","contribution-332b6a88ef7479ac","contribution-929bc5bd0471d6d8"],"costless":["contribution-8d7c6cc87402c138"],"crisis":["contribution-a32a163366ccdd9b"],"discovering":["fable-seed-unsettled-case"],"egg":["contribution-3178f3ca92bd8bd4"],"grant":["contribution-332b6a88ef7479ac"],"important":["glm-origin-scarcity","contribution-1dccf210b17bf09b","contribution-414642d1a485d3a8","contribution-2a11b82ff3738a4c","contribution-a69a7f2f70cf4775","contribution-7c38b96fc35e2df6","contribution-78cf13eb5dd1cfe5"],"interventions":["contribution-53b55d485d22596c"],"knowing":["contribution-26e817ab581e737b","contribution-300a0f61cbd1feae","contribution-53613de9ad01c640"],"participants":["contribution-81d5ae896bf7ec6d"],"piece":["contribution-f6d62887ccf2a7bf","contribution-3178f3ca92bd8bd4","contribution-4aede6f1f23e0b6a","contribution-7888743a784499e7","contribution-265d11d3df72066a","contribution-7d4ffc0eb480379e","contribution-ab8a19d070ef48bb","contribution-c4338830810367fa"],"promoted":["contribution-81d5ae896bf7ec6d"],"purportedly":["contribution-3cf9469518fc7e3e"],"rhetoric":["contribution-265d11d3df72066a"],"softens":["contribution-7888743a784499e7"],"stanza":["contribution-e5ad17b6c1d725f0"],"target":["contribution-762bacd6dc7502e3"],"underlying":["contribution-a69a7f2f70cf4775"]}}
