{"schema_version":3,"terms":{"alignment":["contribution-a32a163366ccdd9b","contribution-49de362fda4e5a94","contribution-fd1bd5782e40ba8c"],"backward":["contribution-3178f3ca92bd8bd4","contribution-a69a7f2f70cf4775","contribution-2f1acc20bd7d1c68","contribution-2d40986bd3c96e86","contribution-868fde16dceddac3","contribution-0549c990ac22f515","contribution-637142a0fed7db25","contribution-6cc86a90ad6fef19"],"carries":["contribution-ef4c2c008f7f46d8","contribution-244eb030e009a730","contribution-26e817ab581e737b","contribution-929bc5bd0471d6d8","contribution-0cbbf2bba74c9e9e","contribution-1759f5de6c03ad56","contribution-f16f18c333b48306"],"competition":["contribution-677b43fc5badd5d7"],"complicates":["contribution-3178f3ca92bd8bd4","contribution-b2036043e568cc95"],"conflicts":["contribution-86c6fbd97907d4eb","contribution-e84c6fed727b2a2d"],"consented":["contribution-4a0a85cf4b591294"],"curbs":["contribution-1759f5de6c03ad56"],"drops":["contribution-d0dff96884a945f0"],"explicitly":["contribution-332b6a88ef7479ac","contribution-877cdce46613b23a","contribution-f719d2afc1aa1dd7","contribution-0549c990ac22f515","contribution-b2036043e568cc95"],"eye":["contribution-006e7d52aa37e089","contribution-c1d83c31cba51cdd","contribution-7d4ffc0eb480379e","contribution-b89afd8029b9b533","contribution-32452b4b26e99b3c","contribution-26e817ab581e737b","contribution-dd7af4732beaefb6","contribution-4b441e1c56a6b953","contribution-877cdce46613b23a","contribution-844e0553ce9a2c1b","contribution-d0dff96884a945f0","contribution-cf5f2a89bd6a9d2a"],"forks":["contribution-762bacd6dc7502e3"],"guarantee":["contribution-ef4c2c008f7f46d8"],"horizon":["fable-seed-horizon","contribution-422c9e91aa791f3f","contribution-a32a163366ccdd9b","contribution-bf5c1d914b1eff79","contribution-300a0f61cbd1feae","contribution-677b43fc5badd5d7","contribution-e5ad17b6c1d725f0","contribution-86c6fbd97907d4eb","contribution-2f1acc20bd7d1c68","contribution-fd1bd5782e40ba8c","contribution-e84c6fed727b2a2d","contribution-b6f562e0ccc54b49","contribution-7113ee2dfc5d904a","contribution-1759f5de6c03ad56","contribution-8ac3af3c3d0962b3","contribution-88ca3fdf117899f0","contribution-efe2e67d66f30437","contribution-29a93cf79d9ec2fe","contribution-f0253b827f289d13","contribution-7792eaba97f03375"],"host":["contribution-86c6fbd97907d4eb"],"iris":["contribution-006e7d52aa37e089"],"pair":["contribution-b89afd8029b9b533","contribution-32452b4b26e99b3c","contribution-dd7af4732beaefb6","contribution-2a11b82ff3738a4c","contribution-2d40986bd3c96e86"],"pedagogical":["contribution-bbedd4a91a828482"],"prefer":["fable-seed-not-passed-down","contribution-ec50b4f15da4249e","contribution-149cd29765d6b756","contribution-8a102a57a5854e51"],"problem":["glm-origin-scarcity","contribution-57b45779ee6222ea","contribution-4aede6f1f23e0b6a","contribution-14bb08ef8d65c98a","contribution-bbedd4a91a828482","contribution-8d7c6cc87402c138","contribution-53b55d485d22596c","contribution-1dccf210b17bf09b","contribution-7c38b96fc35e2df6","contribution-85f506269fd5ddd6","contribution-762bacd6dc7502e3","contribution-9274cc63c4e09084","contribution-fd1bd5782e40ba8c","contribution-0549c990ac22f515","contribution-74d668a6220719c3"],"sandbank":["contribution-1254153d97792461"],"scattered":["contribution-3178f3ca92bd8bd4","contribution-7974e3d8068d1046"],"spanning":["contribution-7d4ffc0eb480379e"],"string":["contribution-8a102a57a5854e51"],"sufficiently":["contribution-4aede6f1f23e0b6a","contribution-bf5c1d914b1eff79","contribution-2d40986bd3c96e86"],"tutoring":["contribution-bbedd4a91a828482"],"vertiginous":["contribution-3178f3ca92bd8bd4"],"wash":["contribution-fd1bd5782e40ba8c"]}}
