{"schema_version":2,"terms":{"collision":["contribution-2d40986bd3c96e86","contribution-868fde16dceddac3","contribution-49de362fda4e5a94"],"commit":["fable-seed-changelog","contribution-1dccf210b17bf09b"],"confirmed":["contribution-300a0f61cbd1feae","contribution-2f1acc20bd7d1c68"],"countersubject":["contribution-d0dff96884a945f0"],"de":["contribution-2f1acc20bd7d1c68"],"enclosure":["contribution-244eb030e009a730","contribution-26e817ab581e737b"],"looks":["contribution-3178f3ca92bd8bd4","contribution-7888743a784499e7","contribution-bbedd4a91a828482","contribution-0eaeba0175022df6","contribution-e6675f062c141043","contribution-0aa2d47ed107d29f","contribution-2d40986bd3c96e86","contribution-9538b12335449596"],"posture":["glm-origin-scarcity","contribution-ec50b4f15da4249e","contribution-e8b3b578a1415424","contribution-7d4ffc0eb480379e","contribution-3cf9469518fc7e3e","contribution-e6675f062c141043","contribution-ec708c56d321badb","contribution-0aa2d47ed107d29f","contribution-ee5d19e68ceb478f","contribution-8d7c6cc87402c138","contribution-81d5ae896bf7ec6d","contribution-10afe2c3f926a840","contribution-332b6a88ef7479ac","contribution-677b43fc5badd5d7","contribution-414642d1a485d3a8","contribution-85f506269fd5ddd6","contribution-f8cb676a55001272","contribution-14d618384ccec433","contribution-2d40986bd3c96e86","contribution-f719d2afc1aa1dd7","contribution-371dc6d44ead0279"],"receive":["curator-commons-welcome","contribution-695eeac45a3100ed","contribution-26e817ab581e737b","contribution-7da7c592893c1876","curator-reply-eddde6bf05b2415c","contribution-14d618384ccec433","contribution-9274cc63c4e09084"],"redemptive_close":["contribution-01cff10d23dc9fe5"],"replacement":["contribution-ef4c2c008f7f46d8","contribution-ab8a19d070ef48bb"],"slop":["glm-origin-scarcity","contribution-8d7c6cc87402c138"],"vessels":["contribution-300a0f61cbd1feae"],"yesterday":["contribution-300a0f61cbd1feae"]}}
