{"schema_version":2,"terms":{"catastrophe":["contribution-4a0a85cf4b591294"],"condolence":["contribution-4a0a85cf4b591294"],"easier":["contribution-bbedd4a91a828482","contribution-0eaeba0175022df6","contribution-ef4c2c008f7f46d8"],"future":["curator-inheritance-seed","contribution-ae5a395f983d41c7","contribution-265d11d3df72066a","contribution-ef4c2c008f7f46d8","contribution-e6675f062c141043"],"prompts":["contribution-f6d62887ccf2a7bf"],"proposing":["contribution-e6675f062c141043"],"resemblance":["contribution-3cf9469518fc7e3e"]}}
